{
  "__comment": "Instructions: https://blakesmods.com/docs/cucumber/tags-config",
  "c:silicon": "oritech:silicon",
  "c:gems/apatite": "null",
  "c:dusts/saltpeter": "immersiveengineering:dust_saltpeter",
  "c:ingots/iridium": "null",
  "c:ingots/invar": "null",
  "c:gems/ruby": "null",
  "c:dusts/niter": "null",
  "c:gems/peridot": "null",
  "c:ingots/tin": "mekanism:ingot_tin",
  "c:gems/sapphire": "null",
  "c:ingots/bronze": "mekanism:ingot_bronze",
  "c:ingots/platinum": "oritech:platinum_ingot",
  "c:ingots/graphite": "null",
  "c:rubbers": "null"
}